{
  "feature_id": "FEAT-009",
  "title": "Export Bundles",
  "description": "Packaging and export engine that assembles agent kits from pipeline run outputs. Maps rendered documents to 12 domain slots via SUBDIR_TO_SLOT, generates kit metadata files (START_HERE, MANIFEST, INDEX, VERSIONS, RUN_RULES, PROOF_LOG), copies core artifacts, produces packaging_manifest.json with SHA-256 hashes, and writes entrypoint.json and version_stamp.json.",
  "category": "core-logic",
  "status": "active",
  "dependencies": [
    "FEAT-001",
    "FEAT-003",
    "FEAT-004"
  ],
  "src_modules": [
    "src/core/kit/build.ts",
    "src/core/kit/entrypoint.ts",
    "src/core/kit/index.ts",
    "src/core/kit/layout.ts",
    "src/core/kit/manifest.ts",
    "src/core/kit/packager.ts",
    "src/core/kit/schemas.ts",
    "src/core/kit/validate.ts",
    "src/core/kit/versions.ts",
    "src/cli/commands/exportBundle.ts"
  ],
  "gates": [
    "GATE-08"
  ],
  "notes": "buildRealKit is the primary entrypoint. packageKit and validateKit are stubs (NotImplementedError). CLI cmdExportBundle is also a stub."
}
